[
  {
    "id": "cmrdewqym02sxtvjmuxq5oatq",
    "clientId": null,
    "documentType": "SPK",
    "documentName": "SPK",
    "documentNumber": null,
    "link": "#",
    "description": "https://drive.google.com/drive/folders/1TZWHwXFJ7E1atAJbR7d-ViKb4GR03m_s",
    "uploadedById": "cmr755gse0000ra4z7bgnpk9h",
    "createdAt": "2026-07-09T11:17:16.031Z",
    "updatedAt": "2026-07-09T11:17:16.031Z"
  },
  {
    "id": "cmrdewqyo02sztvjmxhqm3m78",
    "clientId": null,
    "documentType": "INVOICE",
    "documentName": "Invoice",
    "documentNumber": null,
    "link": "775/INV/HAN/IV/2026",
    "description": "https://drive.google.com/drive/folders/1kzdZHfS3aSdXKDsvGhkLkKiHNgvqNrZW",
    "uploadedById": "cmr755gse0000ra4z7bgnpk9h",
    "createdAt": "2026-07-09T11:17:16.032Z",
    "updatedAt": "2026-07-09T11:17:16.032Z"
  },
  {
    "id": "cmrdewqyp02t1tvjmqjc2vnt4",
    "clientId": null,
    "documentType": "INVOICE",
    "documentName": "Invoice",
    "documentNumber": null,
    "link": "777/INV/HAN/IV/2026",
    "description": "https://drive.google.com/drive/folders/1kzdZHfS3aSdXKDsvGhkLkKiHNgvqNrZW",
    "uploadedById": "cmr755gse0000ra4z7bgnpk9h",
    "createdAt": "2026-07-09T11:17:16.034Z",
    "updatedAt": "2026-07-09T11:17:16.034Z"
  },
  {
    "id": "cmrdewqyr02t3tvjmwrquxrhb",
    "clientId": null,
    "documentType": "INVOICE",
    "documentName": "Invoice",
    "documentNumber": null,
    "link": "776/INV/HAN/IV/2026",
    "description": "https://drive.google.com/drive/folders/1kzdZHfS3aSdXKDsvGhkLkKiHNgvqNrZW",
    "uploadedById": "cmr755gse0000ra4z7bgnpk9h",
    "createdAt": "2026-07-09T11:17:16.035Z",
    "updatedAt": "2026-07-09T11:17:16.035Z"
  },
  {
    "id": "cmrdewqys02t5tvjmoz5r2scf",
    "clientId": null,
    "documentType": "INVOICE",
    "documentName": "Invoice",
    "documentNumber": null,
    "link": "778/INV/HAN/V/2026",
    "description": "https://drive.google.com/drive/folders/1TZWHwXFJ7E1atAJbR7d-ViKb4GR03m_s",
    "uploadedById": "cmr755gse0000ra4z7bgnpk9h",
    "createdAt": "2026-07-09T11:17:16.036Z",
    "updatedAt": "2026-07-09T11:17:16.036Z"
  },
  {
    "id": "cmrdewqys02t7tvjm4w9ruvm7",
    "clientId": null,
    "documentType": "LAINNYA",
    "documentName": "Lainnya",
    "documentNumber": null,
    "link": "0111/HAN/VI/2026",
    "description": "https://drive.google.com/drive/folders/1NDotzTGgkLuAmH6yGJfuGjVgR89l98ME",
    "uploadedById": "cmr755gse0000ra4z7bgnpk9h",
    "createdAt": "2026-07-09T11:17:16.037Z",
    "updatedAt": "2026-07-09T11:17:16.037Z"
  },
  {
    "id": "cmrdewqyt02t9tvjmvjthfbvx",
    "clientId": null,
    "documentType": "SPK",
    "documentName": "SPK",
    "documentNumber": null,
    "link": "https://docs.google.com/document/d/10Qky98g1_ojgUmW_JEY9FoEkP8-Flw_d/edit?usp=drivesdk&ouid=106708798802883491289&rtpof=true&sd=true",
    "description": null,
    "uploadedById": "cmr755gse0000ra4z7bgnpk9h",
    "createdAt": "2026-07-09T11:17:16.038Z",
    "updatedAt": "2026-07-09T11:17:16.038Z"
  },
  {
    "id": "cmrdewqyu02tbtvjmckghbovq",
    "clientId": null,
    "documentType": "SURAT",
    "documentName": "Surat Penawaran",
    "documentNumber": null,
    "link": "https://www.canva.com/design/DAF5ke6WE_Y/Uo5sasB5aDfAX_oT8_ihDA/edit?utm_content=DAF5ke6WE_Y&utm_campaign=designshare&utm_medium=link2&utm_source=sharebutton",
    "description": null,
    "uploadedById": "cmr755gse0000ra4z7bgnpk9h",
    "createdAt": "2026-07-09T11:17:16.039Z",
    "updatedAt": "2026-07-09T11:17:16.039Z"
  },
  {
    "id": "cmrdewqyw02tdtvjmoivti8zl",
    "clientId": null,
    "documentType": "SURAT",
    "documentName": "Surat Tugas, Non PKP, dll",
    "documentNumber": null,
    "link": "https://www.canva.com/design/DAHAQP6GmbQ/C6SVLTbziQO8qc41qrBY3Q/edit?utm_content=DAHAQP6GmbQ&utm_campaign=designshare&utm_medium=link2&utm_source=sharebutton",
    "description": null,
    "uploadedById": "cmr755gse0000ra4z7bgnpk9h",
    "createdAt": "2026-07-09T11:17:16.040Z",
    "updatedAt": "2026-07-09T11:17:16.040Z"
  },
  {
    "id": "cmrdewqyx02tftvjmmte49ytw",
    "clientId": null,
    "documentType": "INVOICE",
    "documentName": "Invoice",
    "documentNumber": null,
    "link": "https://www.canva.com/design/DAGoghEOJ1o/zircNKtOXTbHQsSDbSXcVg/edit",
    "description": null,
    "uploadedById": "cmr755gse0000ra4z7bgnpk9h",
    "createdAt": "2026-07-09T11:17:16.042Z",
    "updatedAt": "2026-07-09T11:17:16.042Z"
  },
  {
    "id": "cmrdewqyy02thtvjmd06z11zz",
    "clientId": null,
    "documentType": "LAINNYA",
    "documentName": "Kwitansi",
    "documentNumber": null,
    "link": "https://www.canva.com/design/DAFy6n_XYvI/ilMiXCqVMIWGtliFDJEBLQ/edit",
    "description": null,
    "uploadedById": "cmr755gse0000ra4z7bgnpk9h",
    "createdAt": "2026-07-09T11:17:16.043Z",
    "updatedAt": "2026-07-09T11:17:16.043Z"
  },
  {
    "id": "cmrdewqz002tjtvjmsi2g0mje",
    "clientId": null,
    "documentType": "LAINNYA",
    "documentName": "Form Magang",
    "documentNumber": null,
    "link": "https://forms.gle/2rbDNx6DaodZqayZA",
    "description": null,
    "uploadedById": "cmr755gse0000ra4z7bgnpk9h",
    "createdAt": "2026-07-09T11:17:16.044Z",
    "updatedAt": "2026-07-09T11:17:16.044Z"
  },
  {
    "id": "cmrdewqz202tltvjm1iud1otl",
    "clientId": null,
    "documentType": "LAINNYA",
    "documentName": "Proposal Penawaran",
    "documentNumber": null,
    "link": "https://www.canva.com/design/DAG2f7t_OQc/RLUd5Jp-Vd8MujTyB7i3dA/edit?utm_content=DAG2f7t_OQc&utm_campaign=designshare&utm_medium=link2&utm_source=sharebutton",
    "description": null,
    "uploadedById": "cmr755gse0000ra4z7bgnpk9h",
    "createdAt": "2026-07-09T11:17:16.047Z",
    "updatedAt": "2026-07-09T11:17:16.047Z"
  },
  {
    "id": "cmrdewqz302tntvjmbj6bpbp8",
    "clientId": null,
    "documentType": "LAINNYA",
    "documentName": "CV, Ratecard, Riders Event",
    "documentNumber": null,
    "link": "https://www.canva.com/design/DAG9Pch_R8s/ZFuBB4qz0MlJHiRXHYe6jA/edit?utm_content=DAG9Pch_R8s&utm_campaign=designshare&utm_medium=link2&utm_source=sharebutton",
    "description": null,
    "uploadedById": "cmr755gse0000ra4z7bgnpk9h",
    "createdAt": "2026-07-09T11:17:16.048Z",
    "updatedAt": "2026-07-09T11:17:16.048Z"
  },
  {
    "id": "cmrdewqz502tptvjmsb4u273z",
    "clientId": null,
    "documentType": "LAINNYA",
    "documentName": "CV Asosiate Trainer",
    "documentNumber": null,
    "link": "https://www.canva.com/design/DAG9UTFURDE/FgLhDfFaR48MMHFrwYTMQA/edit?utm_content=DAG9UTFURDE&utm_campaign=designshare&utm_medium=link2&utm_source=sharebutton",
    "description": null,
    "uploadedById": "cmr755gse0000ra4z7bgnpk9h",
    "createdAt": "2026-07-09T11:17:16.049Z",
    "updatedAt": "2026-07-09T11:17:16.049Z"
  },
  {
    "id": "cmrdewqz602trtvjmdatyzu3f",
    "clientId": null,
    "documentType": "LAINNYA",
    "documentName": "Slide Materi\t2024",
    "documentNumber": null,
    "link": "https://www.canva.com/design/DAFwbzZ2Ae4/hAuk2VywZ7hW2mUG4FGzCg/edit",
    "description": null,
    "uploadedById": "cmr755gse0000ra4z7bgnpk9h",
    "createdAt": "2026-07-09T11:17:16.050Z",
    "updatedAt": "2026-07-09T11:17:16.050Z"
  },
  {
    "id": "cmrdewqz702tttvjmgngzc5sp",
    "clientId": null,
    "documentType": "LAINNYA",
    "documentName": "Slide Materi 2025",
    "documentNumber": null,
    "link": "https://www.canva.com/design/DAG5N4JQ3eg/6QhVrMx31szIIMe5IvD1PQ/edit",
    "description": null,
    "uploadedById": "cmr755gse0000ra4z7bgnpk9h",
    "createdAt": "2026-07-09T11:17:16.051Z",
    "updatedAt": "2026-07-09T11:17:16.051Z"
  },
  {
    "id": "cmrdewqz802tvtvjmzsr4t5q9",
    "clientId": null,
    "documentType": "LAINNYA",
    "documentName": "Slide Materi 2026",
    "documentNumber": null,
    "link": "https://www.canva.com/design/DAG-7VIM6VA/Q9ePx8-MG9y34yIeSZIGhQ/edit",
    "description": null,
    "uploadedById": "cmr755gse0000ra4z7bgnpk9h",
    "createdAt": "2026-07-09T11:17:16.052Z",
    "updatedAt": "2026-07-09T11:17:16.052Z"
  },
  {
    "id": "cmrdewqz802txtvjm18c62p3l",
    "clientId": null,
    "documentType": "LAINNYA",
    "documentName": "Outline Materi",
    "documentNumber": null,
    "link": "https://www.canva.com/design/DAGOdne7pfg/4L6iRecv-q1DD6xRG-Ymcg/edit?utm_content=DAGOdne7pfg&utm_campaign=designshare&utm_medium=link2&utm_source=sharebutton",
    "description": null,
    "uploadedById": "cmr755gse0000ra4z7bgnpk9h",
    "createdAt": "2026-07-09T11:17:16.053Z",
    "updatedAt": "2026-07-09T11:17:16.053Z"
  },
  {
    "id": "cmrdewqza02tztvjm2rcdm6ym",
    "clientId": null,
    "documentType": "LAINNYA",
    "documentName": "Worksheet",
    "documentNumber": null,
    "link": "https://www.canva.com/design/DAG_M0y5Kh8/2tYnouzhcqJPPpLii0Iizw/edit?utm_content=DAG_M0y5Kh8&utm_campaign=designshare&utm_medium=link2&utm_source=sharebutton",
    "description": null,
    "uploadedById": "cmr755gse0000ra4z7bgnpk9h",
    "createdAt": "2026-07-09T11:17:16.054Z",
    "updatedAt": "2026-07-09T11:17:16.054Z"
  },
  {
    "id": "cmrdewqzb02u1tvjmgry82i4i",
    "clientId": null,
    "documentType": "SPK",
    "documentName": "SPK",
    "documentNumber": null,
    "link": "https://drive.google.com/drive/folders/1TZWHwXFJ7E1atAJbR7d-ViKb4GR03m_s",
    "description": null,
    "uploadedById": "cmr755gse0000ra4z7bgnpk9h",
    "createdAt": "2026-07-09T11:17:16.056Z",
    "updatedAt": "2026-07-09T11:17:16.056Z"
  },
  {
    "id": "cmrdewqzd02u3tvjm9ruikhj8",
    "clientId": null,
    "documentType": "INVOICE",
    "documentName": "Invoice",
    "documentNumber": null,
    "link": "https://drive.google.com/drive/folders/1kzdZHfS3aSdXKDsvGhkLkKiHNgvqNrZW",
    "description": null,
    "uploadedById": "cmr755gse0000ra4z7bgnpk9h",
    "createdAt": "2026-07-09T11:17:16.058Z",
    "updatedAt": "2026-07-09T11:17:16.058Z"
  },
  {
    "id": "cmrdewqze02u5tvjmfhy3muwh",
    "clientId": null,
    "documentType": "SURAT",
    "documentName": "Surat-surat",
    "documentNumber": null,
    "link": "https://drive.google.com/drive/folders/1NDotzTGgkLuAmH6yGJfuGjVgR89l98ME",
    "description": null,
    "uploadedById": "cmr755gse0000ra4z7bgnpk9h",
    "createdAt": "2026-07-09T11:17:16.059Z",
    "updatedAt": "2026-07-09T11:17:16.059Z"
  },
  {
    "id": "cmrdewqzg02u7tvjm760yv8o3",
    "clientId": null,
    "documentType": "LAINNYA",
    "documentName": "Kwitansi",
    "documentNumber": null,
    "link": "https://drive.google.com/drive/folders/1LCNZvijRHqoTk4a81sfcgJBXWpIs0Gop",
    "description": null,
    "uploadedById": "cmr755gse0000ra4z7bgnpk9h",
    "createdAt": "2026-07-09T11:17:16.060Z",
    "updatedAt": "2026-07-09T11:17:16.060Z"
  },
  {
    "id": "cmrdewqzh02u9tvjmg6pohzxa",
    "clientId": null,
    "documentType": "LAINNYA",
    "documentName": "Data Magang",
    "documentNumber": null,
    "link": "https://docs.google.com/spreadsheets/d/1ZTipxH1SFfRYrYn0Lg8LWlqvYT71OaCJlcf8CMpv5CI/edit?gid=1741484289#gid=1741484289",
    "description": null,
    "uploadedById": "cmr755gse0000ra4z7bgnpk9h",
    "createdAt": "2026-07-09T11:17:16.062Z",
    "updatedAt": "2026-07-09T11:17:16.062Z"
  },
  {
    "id": "cmrdewqzj02ubtvjm21mqjp4e",
    "clientId": null,
    "documentType": "LAINNYA",
    "documentName": "Modul Magang",
    "documentNumber": null,
    "link": "https://drive.google.com/file/d/1MJTVe-pQ6lMmMlzA-KQVlaad6BWF2iAj/view?usp=drivesdk",
    "description": null,
    "uploadedById": "cmr755gse0000ra4z7bgnpk9h",
    "createdAt": "2026-07-09T11:17:16.063Z",
    "updatedAt": "2026-07-09T11:17:16.063Z"
  },
  {
    "id": "cmrdewqzk02udtvjm6tnh0wib",
    "clientId": null,
    "documentType": "LAINNYA",
    "documentName": "Proposal Hafara Group",
    "documentNumber": null,
    "link": "https://drive.google.com/file/d/1RgLKjCXa66SDWJl9OuVZC3Bj1Yx_vQAh/view?usp=drivesdk",
    "description": null,
    "uploadedById": "cmr755gse0000ra4z7bgnpk9h",
    "createdAt": "2026-07-09T11:17:16.064Z",
    "updatedAt": "2026-07-09T11:17:16.064Z"
  },
  {
    "id": "cmrdewqzl02uftvjmdm68qapw",
    "clientId": null,
    "documentType": "LAINNYA",
    "documentName": "CV, Ratecard, Riders",
    "documentNumber": null,
    "link": "https://drive.google.com/file/d/1_he6Tkyy3bCY7yYtJmQXOOiIRtkZHhIz/view?usp=drivesdk",
    "description": null,
    "uploadedById": "cmr755gse0000ra4z7bgnpk9h",
    "createdAt": "2026-07-09T11:17:16.066Z",
    "updatedAt": "2026-07-09T11:17:16.066Z"
  },
  {
    "id": "cmrdewqzm02uhtvjmdom6cmea",
    "clientId": null,
    "documentType": "LAINNYA",
    "documentName": "CV, dan Riders Event",
    "documentNumber": null,
    "link": "https://drive.google.com/file/d/1PL21biGE4LAJjk933lqM4ekeOBI_XCve/view?usp=drivesdk",
    "description": null,
    "uploadedById": "cmr755gse0000ra4z7bgnpk9h",
    "createdAt": "2026-07-09T11:17:16.067Z",
    "updatedAt": "2026-07-09T11:17:16.067Z"
  },
  {
    "id": "cmrdewqzn02ujtvjmwpc0oqqk",
    "clientId": null,
    "documentType": "LAINNYA",
    "documentName": "CV Associate Trainer",
    "documentNumber": null,
    "link": "https://drive.google.com/drive/folders/1TEYo-E3p9nuuFG1A5vPZ4FbXsPrK4xoo",
    "description": null,
    "uploadedById": "cmr755gse0000ra4z7bgnpk9h",
    "createdAt": "2026-07-09T11:17:16.068Z",
    "updatedAt": "2026-07-09T11:17:16.068Z"
  },
  {
    "id": "cmrdewqzp02ultvjm20rty5v7",
    "clientId": null,
    "documentType": "LAINNYA",
    "documentName": "File Edit Team",
    "documentNumber": null,
    "link": "https://drive.google.com/drive/folders/1gqi-iI0nk1f1aQPvLjvbtHUgta8Q7flI",
    "description": null,
    "uploadedById": "cmr755gse0000ra4z7bgnpk9h",
    "createdAt": "2026-07-09T11:17:16.069Z",
    "updatedAt": "2026-07-09T11:17:16.069Z"
  },
  {
    "id": "cmrdewqzq02untvjmm3bosh5q",
    "clientId": null,
    "documentType": "LAINNYA",
    "documentName": "Mentahan Logo",
    "documentNumber": null,
    "link": "https://drive.google.com/drive/folders/1sttEkvPhsdclwm0SrLGarGDoGW8gMBL9",
    "description": null,
    "uploadedById": "cmr755gse0000ra4z7bgnpk9h",
    "createdAt": "2026-07-09T11:17:16.071Z",
    "updatedAt": "2026-07-09T11:17:16.071Z"
  },
  {
    "id": "cmrdewqzs02uptvjm3wro06j7",
    "clientId": null,
    "documentType": "LAINNYA",
    "documentName": "Foto PNG",
    "documentNumber": null,
    "link": "https://drive.google.com/drive/folders/1pnmqDc1z_yrZBclFZjujJYvKt3qclxuQ",
    "description": null,
    "uploadedById": "cmr755gse0000ra4z7bgnpk9h",
    "createdAt": "2026-07-09T11:17:16.072Z",
    "updatedAt": "2026-07-09T11:17:16.072Z"
  },
  {
    "id": "cmrdewqzt02urtvjmzff4qr0i",
    "clientId": null,
    "documentType": "LAINNYA",
    "documentName": "Database Karyawan",
    "documentNumber": null,
    "link": "https://drive.google.com/drive/folders/1649148eQlJgtVSGXkA9HhYOEpFhUDYPL?usp=drive_link",
    "description": null,
    "uploadedById": "cmr755gse0000ra4z7bgnpk9h",
    "createdAt": "2026-07-09T11:17:16.074Z",
    "updatedAt": "2026-07-09T11:17:16.074Z"
  }
]